free_views_telegram/__init__.py
free_views_telegram/__main__.py
free_views_telegram/auto_proxy.py
free_views_telegram/telegram.py
free_views_telegram/utils.py
free_views_telegram-0.1.12.dist-info/METADATA
free_views_telegram-0.1.12.dist-info/WHEEL
free_views_telegram-0.1.12.dist-info/entry_points.txt
free_views_telegram-0.1.12.dist-info/top_level.txt
free_views_telegram-0.1.12.dist-info/RECORD
