Metadata-Version: 2.4
Name: free-views-telegram
Version: 0.1.12
Summary: A Python library to increase Telegram post views using proxies.
Author: Jack
Author-email: gsksvsksksj@gmail.com
License: MIT
Keywords: telegram,views,proxy,bot
Requires-Dist: requests
